thalex/__init__.py
thalex/thalex.py
thalex-1.3.0.dist-info/METADATA
thalex-1.3.0.dist-info/WHEEL
thalex-1.3.0.dist-info/licenses/LICENSE
thalex-1.3.0.dist-info/RECORD
