Metadata-Version: 2.4
Name: thalex
Version: 1.3.0
Summary: Thalex exchange connector
Project-URL: Homepage, https://github.com/thalextech/thalex_py
Author-email: thalex_py@thalex.com
Maintainer-email: thalex_py@thalex.com
License: Copyright (c) 2024 Thalex Digital Trading Platform Ltd
License-File: LICENSE
Classifier: License :: OSI Approved :: MIT License
Classifier: Operating System :: OS Independent
Classifier: Programming Language :: Python :: 3
Requires-Python: <4,>=3.9
Requires-Dist: cryptography>=42.0.5
Requires-Dist: pyjwt>=2.8.0
Requires-Dist: websockets>=14.1
